pyslp/__init__.py
pyslp/creator.py
pyslp/multicast.py
pyslp/parse.py
pyslp/slpd.py
pyslp/slptool.py
pyslp/utils.py
pyslp/tests/__init__.py
pyslp/tests/test_multicast.py
pyslp/tests/test_parse.py
pyslp/tests/test_slpd.py
pyslp-0.1.7.dist-info/DESCRIPTION.rst
pyslp-0.1.7.dist-info/METADATA
pyslp-0.1.7.dist-info/RECORD
pyslp-0.1.7.dist-info/WHEEL
pyslp-0.1.7.dist-info/metadata.json
pyslp-0.1.7.dist-info/top_level.txt
