Metadata-Version: 1.0
Name: pyslp
Version: 0.1.7
Summary: Service Location Protocol, Version 2
Home-page: UNKNOWN
Author: Seliverstov Maksim
Author-email: Maksim.V.Seliverstov@yandex.ru
License: UNKNOWN
Keywords: slp,openslp,slptool,slpd,service location protocol
Platform: UNKNOWN
